AlteMatrix/__init__.py
AlteMatrix/converter/__init__.py
AlteMatrix/converter/binary.py
AlteMatrix/converter/decimal.py
AlteMatrix/converter/hexadecimal.py
AlteMatrix/converter/octal.py
AlteMatrix/converter/user_defined.py
AlteMatrix/ipanalyzer/__init__.py
AlteMatrix/ipanalyzer/ipv4_address_analyzer.py
AlteMatrix/ipanalyzer/ipv6_address_analyzer.py
AlteMatrix/twos_complement/__init__.py
AlteMatrix/twos_complement/twos_comp.py
AlteMatrix-1.0.0.dist-info/LICENSE
AlteMatrix-1.0.0.dist-info/METADATA
AlteMatrix-1.0.0.dist-info/WHEEL
AlteMatrix-1.0.0.dist-info/top_level.txt
AlteMatrix-1.0.0.dist-info/RECORD
