Metadata-Version: 2.1
Name: AlteMatrix
Version: 1.0.0
Summary: This tool lets you perform some quick tasks for CTFs and Pentesting.
Home-page: https://github.com/Ir0n-c0d3X/AlteMatrix
Author: Ayomide Ayodele-Soyebo
Author-email: midesuperbest@gmail.com
License: UNKNOWN
Platform: UNKNOWN
Classifier: Development Status :: 5 - Production/Stable
Classifier: Intended Audience :: Developers
Classifier: Intended Audience :: Information Technology
Classifier: License :: OSI Approved :: MIT License
Classifier: Natural Language :: English
Classifier: Operating System :: OS Independent
Classifier: Programming Language :: Python :: 3
Classifier: Programming Language :: Python :: 3.10
Classifier: Topic :: Security
Classifier: Topic :: Security :: Cryptography
Requires-Python: >=3.10
License-File: LICENSE
